<?xml version = '1.0' encoding = 'UTF-8'?>
<TableProxyOraclev20c class="oracle.dbtools.crest.model.design.storage.oracle.v20c.TableProxyOraclev20c" name="HZS_RENTAL" directorySegmentName="seg_0" id="63C6323B-A012-2DBD-39B9-4EC23AF1FF47">
<createdBy>25103</createdBy>
<createdTime>2025-03-25 19:13:11 UTC</createdTime>
<ownerDesignName>edited</ownerDesignName>
<logging>YES</logging>
<partitionedRowMovement>DISABLE</partitionedRowMovement>
<temporaryChanged>false</temporaryChanged>
<accessDriverType>oracle_loader</accessDriverType>
<rejectLimit></rejectLimit>
<columnProxies itemClass="oracle.dbtools.crest.model.design.storage.oracle.v12c.ColumnProxyOraclev12c">
<ColumnProxy name="COPY_ID" id="3C5988F5-1211-A301-C093-CAC99B23A707">
<createdBy>25103</createdBy>
<createdTime>2025-03-27 16:58:04 UTC</createdTime>
<ownerDesignName>edited</ownerDesignName>
</ColumnProxy>
<ColumnProxy name="EXPECTED_RETURN_DATE" id="4E804355-BFB5-8445-7BDB-7ABCAEBDABB9">
<createdBy>25103</createdBy>
<createdTime>2025-03-25 19:13:11 UTC</createdTime>
<ownerDesignName>edited</ownerDesignName>
</ColumnProxy>
<ColumnProxy name="RENTAL_STATUS" id="4FBAE138-7970-F9EC-20FA-59ACCA46AF93">
<createdBy>25103</createdBy>
<createdTime>2025-03-25 19:13:11 UTC</createdTime>
<ownerDesignName>edited</ownerDesignName>
</ColumnProxy>
<ColumnProxy name="RENTAL_ID" id="5ED8779D-C136-073B-5FB0-DB7A35CB269B">
<createdBy>25103</createdBy>
<createdTime>2025-03-25 19:13:11 UTC</createdTime>
<ownerDesignName>edited</ownerDesignName>
</ColumnProxy>
<ColumnProxy name="BORROW_DATE" id="6107F066-161D-BD16-7322-B1304453810A">
<createdBy>25103</createdBy>
<createdTime>2025-03-25 19:13:11 UTC</createdTime>
<ownerDesignName>edited</ownerDesignName>
</ColumnProxy>
<ColumnProxy name="INVOICE_ID" id="DC80CC3C-3BDA-818D-C9A2-D7EB28A0D936">
<createdBy>25103</createdBy>
<createdTime>2025-03-25 19:13:11 UTC</createdTime>
<ownerDesignName>edited</ownerDesignName>
</ColumnProxy>
<ColumnProxy name="ACTUAL_RETURN_DATE" id="F5112503-D942-4970-561E-9E41311515D0">
<createdBy>25103</createdBy>
<createdTime>2025-03-25 19:13:11 UTC</createdTime>
<ownerDesignName>edited</ownerDesignName>
</ColumnProxy>
<ColumnProxy name="CUSTOMER_ID" id="FD92D01F-C519-FBF4-2E42-452BFEBF71F6">
<createdBy>25103</createdBy>
<createdTime>2025-03-25 19:13:11 UTC</createdTime>
<ownerDesignName>edited</ownerDesignName>
</ColumnProxy>
</columnProxies>
<foreignKeys>
<ForeignKey class="oracle.dbtools.crest.model.design.storage.oracle.v10g.FKProxyOraclev10g" name="HZS_RENTAL_HZS_BOOK_COPY_FK" id="398217BB-885A-481B-7238-003F3B5AFC13">
<createdBy>25103</createdBy>
<createdTime>2025-03-27 16:58:04 UTC</createdTime>
<ownerDesignName>edited</ownerDesignName>
</ForeignKey>
<ForeignKey class="oracle.dbtools.crest.model.design.storage.oracle.v10g.FKProxyOraclev10g" name="HZS_RENTAL_HZS_INVOICE_FK" id="662232F9-834E-CA24-DFCE-F5F1A0DCB39A">
<createdBy>25103</createdBy>
<createdTime>2025-03-25 19:13:11 UTC</createdTime>
<ownerDesignName>edited</ownerDesignName>
</ForeignKey>
<ForeignKey class="oracle.dbtools.crest.model.design.storage.oracle.v10g.FKProxyOraclev10g" name="HZS_RENTAL_HZS_CUSTOMER_FK" id="8E729507-65CA-8329-67D7-34AD44A55E8E">
<createdBy>25103</createdBy>
<createdTime>2025-03-25 19:13:11 UTC</createdTime>
<ownerDesignName>edited</ownerDesignName>
</ForeignKey>
</foreignKeys>
<primaryKeys>
<PrimaryKey class="oracle.dbtools.crest.model.design.storage.oracle.v10g.PKProxyOraclev10g" name="HZS_RENTAL_PK" id="5E15449E-F6C2-8D6B-A01D-AD712F598207">
<createdBy>25103</createdBy>
<createdTime>2025-03-25 19:13:11 UTC</createdTime>
<ownerDesignName>edited</ownerDesignName>
<indexSort>SORTED</indexSort>
</PrimaryKey>
</primaryKeys>
</TableProxyOraclev20c>